[{
  "_id": {
    "$oid": "6458ed4959327103d7414a06"
  },
  "cocktail": "Boulevardier",
  "description": "A lesser known cocktail and a variant on the Negroni. For this one add all the ingredients to a mixing glass and stir down with ice. Garnish with a twist of orange peel.",
  "recipe": "20ml of Campari ,,20ml of Vermouth ,,20ml Rye Whiskey",
  "ingredients": [
    "Liqueur (Campari)",
    "Whiskey (Rye)",
    "Vermouth (Red)"
  ],
  "imgLink": "https://www.liquor.com/thmb/boQt-AytPVa9EOUN_tRTo7EcJsg=/750x0/filters:no_upscale():max_bytes(150000):strip_icc():format(webp)/__opt__aboutcom__coeus__resources__content_migration__liquor__2019__09__12094720__Boulevardier-720x720-recipe-53da547e8cfc4bd79a393ac99891f5ba.jpg",
  "__v": 0
},{
  "_id": {
    "$oid": "6459d318973aeb6c6d0a8f2b"
  },
  "cocktail": "Manhattan",
  "description": "Simple 1800s cocktail, add ingredients to a glass and stir. Serve neat and garnish with an orangepeel or maraschino cherry",
  "recipe": "50ml of Rye Whiskey ,,10ml of Sweet Red Vermouth,,2-3 dashes of bitters",
  "ingredients": [
    "Whiskey (Rye)",
    "Vermouth (Red)"
  ],
  "imgLink": "https://crazymasalafood.com/wp-content/images/2023/02/2manhattan.jpg.webp",
  "__v": 0
},{
  "_id": {
    "$oid": "6457cc49aa63f7f421b49f23"
  },
  "cocktail": "Martini (Vodka)",
  "description": "A classic cocktail considered the height of class. For this one just add all the ingredients to a mixing glass and stir down with ice or shake if you prefer more dilute. Garnish with a twist of lemon rind or some olives. ",
  "recipe": "60ml of Vodka ,,10-15ml of Vermouth (~5ml for dry, 10ml but pour it out again for extra dry) ,,Optional: 10-20ml olive brine for a dirty martini",
  "ingredients": [
    "Vodka",
    "Vermouth (White)"
  ],
  "imgLink": "https://www.liquor.com/thmb/uiVEGvb2jIR-Y_IyKZCIPrxrt-U=/750x0/filters:no_upscale():max_bytes(150000):strip_icc():format(webp)/vodka-martini-1500x1500-hero-080af5bb8ff04851a9c0ecf77a88a818.jpg",
  "__v": 0
},{
  "_id": {
    "$oid": "6457b5330855c7ad24e3dcc2"
  },
  "cocktail": "Old Fashioned (Bourbon)",
  "description": "A classic cocktail as simple as they come. For this one just add all the ingredients to a mixing glass and stir down with ice. Garnish with a twist of orange peel",
  "recipe": "60ml of Bourbon ,,3-4 dashes of bitters ,,10-15ml of sugarsyrup",
  "ingredients": [
    "Bourbon"
  ],
  "imgLink": "https://www.liquor.com/thmb/NtKmemhR70zK-UiAaxi2aO9Fgng=/750x0/filters:no_upscale():max_bytes(150000):strip_icc():format(webp)/__opt__aboutcom__coeus__resources__content_migration__liquor__2018__05__08113350__bourbon-old-fashioned-720x720-recipe-ade6f7780c304999be3577e565c9bcdd.jpg",
  "__v": 0
},{
  "_id": {
    "$oid": "6458ee9859327103d7414a08"
  },
  "cocktail": "Margarita",
  "description": "A taste of mexico, the go to cocktail for a great night. Add all the ingredients and shake over ice. Serve in a glass with a salt rim.",
  "recipe": "45ml of Tequila ,,15ml of Cointreau ,,30ml Lime juice ,,Optional: 10-15ml Sugar syrup if you like things sweeter",
  "ingredients": [
    "Tequila",
    "Liqueur (Orange)"
  ],
  "imgLink": "https://img.jamieoliver.com/jamieoliver/recipe-database/oldImages/large/1198_1_1436865046.jpg?tr=w-800,h-1066",
  "__v": 0
},{
  "_id": {
    "$oid": "6459fd505ed003767e04f720"
  },
  "cocktail": "Daiquiri",
  "description": "A drink with tropical vibes best shaken. Serve neat and garnish with a lime.",
  "recipe": "60ml of White Rum ,,30ml lime juice ,,15ml sugar syrup",
  "ingredients": [
    "Rum (White)"
  ],
  "imgLink": "https://www.thespruceeats.com/thmb/TB0bX315BLqjBt7Nwo1BSQ6j7v4=/750x0/filters:no_upscale():max_bytes(150000):strip_icc():format(webp)/SES-classic-daiquiri-recipe-759294-hero-4-2ce74e7410a849118cac537834a36ea4.jpg",
  "__v": 0
},{
  "_id": {
    "$oid": "645a02655ed003767e04f726"
  },
  "cocktail": "Long Island Ice Tea",
  "description": "The big coctail everyone has knows. Add all, shake, and top with cola. Garnish with a lemon wedge or lime wheel",
  "recipe": "15ml of Vodka ,,15ml of Gin ,,15ml of Tequila ,,15ml of White Rum,, 15ml of Triple Sec ,,15ml sugar syrup ,,15ml Lemon juice ,,15ml Lime Juice,, Cola ,, Optional: 30ml of either lime or lemon juice is fine if you only have 1",
  "ingredients": [
    "Vodka",
    "Gin (Dry)",
    "Rum (White)",
    "Tequila",
    "Liqueur (Orange)"
  ],
  "imgLink": "https://crazymasalafood.com/wp-content/images/2023/02/2Long-Island-Iced-tea.jpg.webp",
  "__v": 0
},{
  "_id": {
    "$oid": "645a03a25ed003767e04f728"
  },
  "cocktail": "Caipirinha",
  "description": "The taste of Brazi. Build this one in the glass. Muddle (crush) the limes in the bottom of the glass. Add the sugar, fill with crushed ice and pour the Cachaça over the top and stir. Garnish with a lime wheel",
  "recipe": "60ml of Cachaça ,,3-4 Lime wedges ,,15ml sugar syrup",
  "ingredients": [
    "Cachaça"
  ],
  "imgLink": "https://crazymasalafood.com/wp-content/images/2023/02/Caipirinha.jpg.webp",
  "__v": 0
},{
  "_id": {
    "$oid": "645a00535ed003767e04f724"
  },
  "cocktail": "Espresso Martini",
  "description": "A pick-me-up on a long night or a coffee for a hot day. Add the ingredients to a shaker and shake aggressively (To get that nice foam). Garnish with a few coffee beans.",
  "recipe": "30ml of Vodka ,,30ml of Coffee liqueur ,,15ml sugar syrup ,, 30ml of espresso (1 shot) ,, Optional: 15ml of Chocolate Liqueur",
  "ingredients": [
    "Vodka",
    "Liqueur (Coffee)"
  ],
  "imgLink": "https://crazymasalafood.com/wp-content/images/2023/02/2-Espresso-Martini-696x696.jpg.webp",
  "__v": 0
},{
  "_id": {
    "$oid": "6459fecd5ed003767e04f722"
  },
  "cocktail": "Mojito",
  "description": "A refreshing drink for a hot day. Place the lime and mint at the bottom of the glass and muddle (crush together). Add the rum and sugar, some ice, and top with soda. Garnish with a lime wheel and a mint sprig. Pro Tip: If you 'crack' the mint first by placing it in your palm and smaking with the back of your hand, you release the flavour more.",
  "recipe": "60ml of White Rum ,,Half a lime cut to wedges,, 5-10 large mint leaves ,,15ml sugar syrup ,,Soda water",
  "ingredients": [
    "Rum (White)"
  ],
  "imgLink": "https://crazymasalafood.com/wp-content/images/2023/02/2-Mojito-960x1440.jpg.webp",
  "__v": 0
}]